odoo/addons/cooperator_account_banking_mandate/__init__.py
odoo/addons/cooperator_account_banking_mandate/__manifest__.py
odoo/addons/cooperator_account_banking_mandate/models/__init__.py
odoo/addons/cooperator_account_banking_mandate/models/subscription_request.py
odoo/addons/cooperator_account_banking_mandate/views/subscription_request_views.xml
odoo_addon_cooperator_account_banking_mandate-16.0.0.2.2.dist-info/METADATA
odoo_addon_cooperator_account_banking_mandate-16.0.0.2.2.dist-info/WHEEL
odoo_addon_cooperator_account_banking_mandate-16.0.0.2.2.dist-info/top_level.txt
odoo_addon_cooperator_account_banking_mandate-16.0.0.2.2.dist-info/RECORD
