Metadata-Version: 2.1
Name: odoo-addon-cooperator-account-banking-mandate
Version: 16.0.0.2.2
Summary: This module adds mandate selection to cooperator subscription request.
Home-page: https://coopdevs.org
Author: Som IT Cooperatiu SCCL
License: AGPL-3
Classifier: Programming Language :: Python
Classifier: Framework :: Odoo
Classifier: Framework :: Odoo :: 16.0
Classifier: License :: OSI Approved :: GNU Affero General Public License v3
Requires-Python: >=3.10
Requires-Dist: odoo-addon-account-banking-mandate<16.1dev,>=16.0dev
Requires-Dist: odoo-addon-account-banking-sepa-direct-debit<16.1dev,>=16.0dev
Requires-Dist: odoo-addon-cooperator<16.1dev,>=16.0dev
Requires-Dist: odoo<16.1dev,>=16.0a
